<?xml version="1.0" encoding="UTF-8"?>

<mule xmlns:http="http://www.mulesoft.org/schema/mule/http" xmlns="http://www.mulesoft.org/schema/mule/core"
	xmlns:doc="http://www.mulesoft.org/schema/mule/documentation"
	xmlns:xsi="http://www.w3.org/2001/XMLSchema-instance" xsi:schemaLocation="http://www.mulesoft.org/schema/mule/core http://www.mulesoft.org/schema/mule/core/current/mule.xsd
http://www.mulesoft.org/schema/mule/http http://www.mulesoft.org/schema/mule/http/current/mule-http.xsd">
	<sub-flow name="patch-subscription-clientSub_Flow" doc:id="5984247c-ebe5-4016-b24d-2a9b59202450" >
		<http:request method="PATCH" doc:name="patch-subscription-service-papi" doc:id="f4f4f83e-f6d9-4c22-9c8d-80848d7c5ad2" config-ref="HTTP_Request_configuration-service-papi-services" path="${service-papi-services.path.subscription}" >
			<http:headers ><![CDATA[#[output application/java
---
{
	"X-CORRELATION-ID" : correlationId,
	"client_id": p('service-papi-services.client_id'),
	"client_secret" : p('service-papi-services.client_secret'),
	"origenTransaccion" : "mvne-xapi-services"
}]]]></http:headers>
			<http:uri-params ><![CDATA[#[output application/java
---
{
	"connectionNumber" : vars.connectionNumber
}]]]></http:uri-params>
		</http:request>
	</sub-flow>
</mule>
