{
  "WSResponseHeader": {
    "System": {
      "name": "MIETB",
      "correlationID": "Identificador único de la petición",
      "processingServer": "SRV-BOT-01"
    },
    "Service": {
      "status": "OK",
      "responseDate": "2025-07-25T12:36:38.9784777Z",
      "processingServer": "SRV-BOT-01",
      "statusDetail": [
        {
          "errorCode": "OK_01",
          "errorDetailCode": "Consulta de información de pago realizada correctamente",
          "errorMessage": "Proceso exitoso",
          "errorMessageUser": "Consulta de información de pago realizada correctamente"
        }
      ]
    },
    "Property": []
  },
  "WSResponseBody": {
    "Phone": "6013103732",
    "Billing_Account": "15052876387",
    "Billing_Number": "FAC2024001234",
    "Billing_Number_PSE": "PSE2024001234",
    "Billing_Address": "Calle 123 #45-67, Bogotá",
    "Billing_Phone": "6013103732",
    "Email": "cliente@email.com",
    "Billed_Period": "2024-12",
    "Billing_Cutoff_Date": "2024-12-15",
    "Payment_Date": "2024-12-25",
    "Payday_Limit": "2024-12-30",
    "State": "Vencida",
    "Delivery_Type": "Digital",
    "Extemporaneous": false,
    "Is_Receipt_Of_Payment": false,
    "Invoice_Origin": "Sistema de Facturación",
    "Barcode": "12345678901234567890",
    "Value_Original": {
      "Value": 125000,
      "Value_Str": "$125,000.00"
    },
    "Value_Service": {
      "Value": 89000,
      "Value_Str": "$89,000.00"
    },
    "Value_Final": {
      "Value": 125000,
      "Value_Str": "$125,000.00"
    },
    "Concepts": {
      "Reconnected": {
        "Cost": 15000,
        "Cost_Usr": "$15,000.00",
        "Date": "2024-12-10"
      },
      "Suspend": {
        "Cost": 10000,
        "Cost_Usr": "$10,000.00",
        "Date": "2024-12-05"
      }
    },
    "Information_Value": [
      {
        "Date": "2024-12-20",
        "Message": "El valor a pagar incluye servicios adicionales del mes anterior"
      }
    ],
    "Payment": {
      "Bank": "Bancolombia",
      "Payment_Date": "2024-12-28",
      "Type": "Digital",
      "Value": {
        "Value": 125000,
        "Value_Str": "$125,000.00"
      }
    },
    "Adjust": {
      "Date": "2024-12-15",
      "Num_PQR": "PQR2024001234",
      "Origin": "Reclamo Cliente",
      "Value": {
        "Value": -5000,
        "Value_Str": "-$5,000.00"
      }
    }
  }
}