<?xml version="1.0" encoding="UTF-8"?>

<mule xmlns:ee="http://www.mulesoft.org/schema/mule/ee/core" xmlns="http://www.mulesoft.org/schema/mule/core"
	xmlns:doc="http://www.mulesoft.org/schema/mule/documentation"
	xmlns:xsi="http://www.w3.org/2001/XMLSchema-instance" xsi:schemaLocation="http://www.mulesoft.org/schema/mule/core http://www.mulesoft.org/schema/mule/core/current/mule.xsd
http://www.mulesoft.org/schema/mule/ee/core http://www.mulesoft.org/schema/mule/ee/core/current/mule-ee.xsd">
	<sub-flow name="get-offer-orchestratorSub_Flow" doc:id="908854da-39a7-4dd8-9c89-289046cc2fde" >
		<flow-ref doc:name="Go to Client" doc:id="2f35ec67-0488-4920-8766-16fea67096d7" name="get-offer-clientSub_Flow"/>
		<ee:transform doc:name="Parse Body to Json" doc:id="d24c9175-48dd-4e40-ab21-53d431f8b25c" >
			<ee:message >
				<ee:set-payload ><![CDATA[%dw 2.0
output application/json
---
payload]]></ee:set-payload>
			</ee:message>
		</ee:transform>
	</sub-flow>
</mule>
